setup.py
IORedprint/__init__.py
IORedprint.egg-info/PKG-INFO
IORedprint.egg-info/SOURCES.txt
IORedprint.egg-info/dependency_links.txt
IORedprint.egg-info/top_level.txt