Metadata-Version: 1.1
Name: IORedprint
Version: 1.0.0
Summary: xd
Home-page: https://github.com/raflorez/IORedprint.git
Author: Elsa Bandija
Author-email: elsa_bandija@gmail.com
License: GPLv3
Platform: UNKNOWN
Classifier: Programming Language :: Python :: 3
Classifier: License :: OSI Approved :: GNU General Public License v3 (GPLv3)
Classifier: Development Status :: 4 - Beta
Classifier: Intended Audience :: Developers
Classifier: Operating System :: OS Independent
